{
	"greeting": "Hi",
	"name": "Jasell",
	"greetingText": "Sayang kuuu Cintakuu!!!",
	"wishText": "Wish You All The BEST! ;)",
	"imagePath": "img/Farida.png",
	"text1": "Hari ini hari Ulang Tahun Kamu ya!!!!",
	"textInChatBox": "Selamat Ulang Tahun ya semoga cita citamu dapat terwujud aamiin.",
	"sendButtonLabel": "Send",
	"text2": "Cuma itu sih yang mau aku ucapin",
	"text3": "Tapi",
	"text4": "Gajadi, Aku pingin sesuatu yang",
	"text4Adjective": "Perfect",
	"text5Entry": "Karena,",
	"text5Content": "You are my Perfect Girl",
	"smiley": ":)",
	"bigTextPart1": "S",
	"bigTextPart2": "O",
	"wishHeading": "Happy Birthday My Love!",
	"outroText": "wish you all the best",
	"replayText": "kalau udah diliat buka lagi web yang tadi aku kasihh ya sayangg",
	"outroSmiley": ":)"
}
